valohai_local_run/__init__.py
valohai_local_run/cli.py
valohai_local_run/compat.py
valohai_local_run/consts.py
valohai_local_run/download.py
valohai_local_run/excs.py
valohai_local_run/executor.py
valohai_local_run/inputs.py
valohai_local_run/tee.py
valohai_local_run/utils.py
valohai_local_run-0.2.2.dist-info/METADATA
valohai_local_run-0.2.2.dist-info/RECORD
valohai_local_run-0.2.2.dist-info/WHEEL
valohai_local_run-0.2.2.dist-info/entry_points.txt
valohai_local_run-0.2.2.dist-info/top_level.txt
