Metadata-Version: 2.1
Name: valohai-local-run
Version: 0.2.2
Summary: UNKNOWN
Home-page: UNKNOWN
Author: Valohai
Author-email: hait@valohai.com
License: MIT
Platform: UNKNOWN
Provides-Extra: online
Requires-Dist: valohai-yaml (>=0.5)
Requires-Dist: click (>=6.7)
Provides-Extra: online
Requires-Dist: requests (>=2.0.0); extra == 'online'
